[
  {
    "document_number": null,
    "document_type": null,
    "document_title": null,
    "issue_date": null,
    "issue_year": 2014,
    "issuing_agency": null,
    "effective_date": null,
    "source_file": "Luật-52-2014-QH13",
    "confidential_level": "Công Khai",
    "source": "Luật-52-2014-QH13.txt",
    "field": "hon_nhan_gia_dinh",
    "chunk_title": "None - Preamble",
    "law_field": "hon_nhan_gia_dinh",
    "entity_type": "[\"nan_nhan\", \"nguoi_lao_dong\", \"ca_nhan\", \"to_chuc\"]",
    "penalties": "[]"
  }
]