[
  {
    "document_number": "67/2022/NĐ-CP",
    "document_type": "Nghị định",
    "document_title": "Sửa đổi, bổ sung Điều 4 Nghị định số 166/2018/NĐ-CP ngày 25 tháng 12 năm 2018 của Chính phủ quy định thẩm quyền, trình tự, thủ tục lập, thẩm định, phê duyệt quy hoạch, dự án bảo quản, tu bổ, phục hồi di tích lịch sử - văn hóa, danh lam thắng cảnh",
    "issue_date": "21/09/2022",
    "issue_year": 2022,
    "issuing_agency": "Chính phủ",
    "effective_date": "21/09/2022",
    "source_file": "Nghị định-67-2022-NĐ-CP",
    "confidential_level": "Công Khai",
    "source": "Nghị định-67-2022-NĐ-CP.txt",
    "field": "tai_chinh_thue",
    "chunk_title": "Sửa đổi, bổ sung Điều 4 Nghị định số 166/2018/NĐ-CP ngày 25 tháng 12 năm 2018 của Chính phủ quy định thẩm quyền, trình tự, thủ tục lập, thẩm định, phê duyệt quy hoạch, dự án bảo quản, tu bổ, phục hồi di tích lịch sử - văn hóa, danh lam thắng cảnh - Preamble",
    "law_field": "tai_chinh_thue",
    "entity_type": "[\"ca_nhan\", \"to_chuc\"]",
    "penalties": "[]"
  }
]